{
  "account": "DriftProtocol",
  "scrapingDate": "2025-05-27T16:21:20.830Z",
  "targetPostCount": 30,
  "totalPosts": 30,
  "posts": [
    {
      "timestamp": "2025-05-21T15:55:10.000Z",
      "tweetText": "Drift Institutional is here.\n\nA new white-glove service to help institutions bring real-world assets onchain into \n@solana\n's DeFi ecosystem — starting with a first-of-its-kind Institutional Pool for Apollo’s tokenized credit fund.",
      "isRepost": false,
      "originalAuthor": "DriftProtocol",
      "postUrl": "/DriftProtocol/status/1925218821562097899"
    },
    {
      "timestamp": "2025-05-26T15:39:49.000Z",
      "tweetText": "Where do you think $SOL goes from here?\n\n= $200 next\n= $150 next",
      "isRepost": false,
      "originalAuthor": "DriftProtocol",
      "postUrl": "/DriftProtocol/status/1927026898934104260"
    },
    {
      "timestamp": "2025-05-23T13:00:08.000Z",
      "tweetText": "FUEL Rewards Program Update\n\nThe FUEL Rewards Program is in its final phase and will be ending soon — the official end date will be announced shortly.\n\nHere’s what you need to know",
      "isRepost": false,
      "originalAuthor": "DriftProtocol",
      "postUrl": "/DriftProtocol/status/1925899549849145626"
    },
    {
      "timestamp": "2025-05-23T13:00:12.000Z",
      "tweetText": "A claim page will be available a few weeks after the FUEL program concludes\n\nThere will be a new version of the incentives program once the FUEL claim is concluded. Stay tuned!",
      "isRepost": false,
      "originalAuthor": "DriftProtocol",
      "postUrl": "/DriftProtocol/status/1925899563732271455"
    },
    {
      "timestamp": "2025-05-23T13:00:15.000Z",
      "tweetText": "In line with our commitment to fairness:\n\n• Wallets identified for wash trading will be disqualified for rewards\n• Volume generated through wash trading will not count towards milestone tracking.\n\nFor any questions and further updates, join Drift's Discord channel -",
      "isRepost": false,
      "originalAuthor": "DriftProtocol",
      "postUrl": "/DriftProtocol/status/1925899577044906445"
    },
    {
      "timestamp": "2025-05-22T17:05:22.000Z",
      "tweetText": "Bitcoin on Solana? It’s happening\n\nAnd there’s a delta-neutral strategy that can yield up to 19% APR using $zBTC and $cbBTC\n\nHere’s how you can do it with \n@DriftProtocol",
      "isRepost": true,
      "originalAuthor": "Kaleve_",
      "postUrl": "/Kaleve_/status/1925598876548911129"
    },
    {
      "timestamp": "2025-05-22T17:47:25.000Z",
      "tweetText": "Imagine earning THAT yield on your $BTC\n\nNow, stop imagining and deposit on Drift to earn $ZEUS rewards.\n\n\n@ZeusNetworkHQ",
      "isRepost": false,
      "originalAuthor": "DriftProtocol",
      "postUrl": "/DriftProtocol/status/1925609458451063052"
    },
    {
      "timestamp": "2025-05-22T17:47:28.000Z",
      "tweetText": "Deposit Now:",
      "isRepost": false,
      "originalAuthor": "DriftProtocol",
      "postUrl": "/DriftProtocol/status/1925609470711013702"
    },
    {
      "timestamp": "2025-05-22T17:47:31.000Z",
      "tweetText": "Disclaimer: Yields are variable and may fluctuate based on market conditions. Past performance is not indicative of future results.",
      "isRepost": false,
      "originalAuthor": "DriftProtocol",
      "postUrl": "/DriftProtocol/status/1925609482891194463"
    },
    {
      "timestamp": "2025-05-22T11:35:56.000Z",
      "tweetText": "I’m delighted to be hosting a fireside chat with Cynthia Lo Bessette at \n@SolanaConf\n as part of \n@DriftProtocol\n’s institutional foray.\n\nLet’s accelerate",
      "isRepost": true,
      "originalAuthor": "davijlu",
      "postUrl": "/davijlu/status/1925515970056974722"
    },
    {
      "timestamp": "2025-05-22T11:17:36.000Z",
      "tweetText": "Had a super awesome time at \n@DriftProtocol\n Defi Day!! Big shoutout to \n@spicycilipadi\n for the amazing job on the event!!! So many beautiful details...",
      "isRepost": true,
      "originalAuthor": "lukasisdeco",
      "postUrl": "/lukasisdeco/status/1925511358407135348"
    },
    {
      "timestamp": "2025-05-21T23:33:32.000Z",
      "tweetText": "Big deal day for Solana DeFi.\n\nInstitutional yield once reserved for private credit desks is coming",
      "isRepost": true,
      "originalAuthor": "solana",
      "postUrl": "/solana/status/1925334172337307679"
    },
    {
      "timestamp": "2025-05-21T23:57:31.000Z",
      "tweetText": "SOON joined \n@DriftProtocol\n’s DeFi Day for a sharp panel on “The Infrastructure Layers of DeFi,” moderated by \n@bigz_pubkey\n with industry leaders: \n@soleconomist\n \n@MidwitMilhouse\n \n@justsayuluvjo\n\n\nKey takeaway: Drift & Solana are paving the way for institutions and RWAs. SOON is",
      "isRepost": true,
      "originalAuthor": "soon_svm",
      "postUrl": "/soon_svm/status/1925340210499383346"
    },
    {
      "timestamp": "2025-05-21T16:12:33.000Z",
      "tweetText": ".\n@Lightspeedpodhq\n live at \n@DriftProtocol\n DeFi day",
      "isRepost": true,
      "originalAuthor": "Evanzsolomon",
      "postUrl": "/Evanzsolomon/status/1925223197412073995"
    },
    {
      "timestamp": "2025-05-21T21:51:24.000Z",
      "tweetText": "Phase 1 of Solana growth: Issue Solana-native assets\n\nPhase 2 Solana matures: Build the infra to bring all assets and liquidity from other ecosystems to \n@solana\n like $BTC and $DOGE\n\nYou heard it from \n@calilyliu\n & \n@cindyleowtt\n. Time to ship",
      "isRepost": true,
      "originalAuthor": "justsayuluvjo",
      "postUrl": "/justsayuluvjo/status/1925308472435876181"
    },
    {
      "timestamp": "2025-05-21T22:22:23.000Z",
      "tweetText": "Was amazing to sit and chat with \n@KMSmithDC\n of \n@SolanaInstitute\n at Drift DeFi Day at \n@SolanaConf\n.  Big thank you to \n@davijlu\n \n@cindyleowtt\n and the whole \n@DriftProtocol\n team for a great event. \nDon’t tell DC, but talking to Builders >> talking to Regulators.",
      "isRepost": true,
      "originalAuthor": "xethalis",
      "postUrl": "/xethalis/status/1925316268334178599"
    },
    {
      "timestamp": "2025-05-21T19:13:28.000Z",
      "tweetText": "Fast transactions are only half the battle: institutions need the guarantee that their transaction will land\n\nA full-stack infra panel - thanks  \n@soleconomist\n \n@MidwitMilhouse\n \n@justsayuluvjo\n for the fantastic conversation (and \n@DriftProtocol\n for hosting!)",
      "isRepost": true,
      "originalAuthor": "raikucom",
      "postUrl": "/raikucom/status/1925268726947225774"
    },
    {
      "timestamp": "2025-05-21T16:16:45.000Z",
      "tweetText": "Here at DRIFT DEFI DAY \n\nThe panels are massively educational. Had a chance to learn about what institutions really want & need from the adoption of blockchain tech, & of course DEFI tools.\n\n\n@DriftProtocol\n \n@cindyleowtt\n \n@davijlu\n \n\n@Blockworks_\n\n$drift #drift #sol $sol #solana",
      "isRepost": true,
      "originalAuthor": "MoonEkko33",
      "postUrl": "/MoonEkko33/status/1925224252346642602"
    },
    {
      "timestamp": "2025-05-21T15:55:19.000Z",
      "tweetText": "Institutions are coming onchain.\n\nDrift Institutional brings DeFi utility to RWAs with leverage, yield, and isolated risk baked in.\n\nReal assets. Real capital. Real DeFi.",
      "isRepost": false,
      "originalAuthor": "DriftProtocol",
      "postUrl": "/DriftProtocol/status/1925218857708646907"
    },
    {
      "timestamp": "2025-05-21T15:55:21.000Z",
      "tweetText": "Learn more:",
      "isRepost": false,
      "originalAuthor": "DriftProtocol",
      "postUrl": "/DriftProtocol/status/1925218869544939634"
    },
    {
      "timestamp": "2025-05-21T15:55:13.000Z",
      "tweetText": "This is a new chapter for internet capital markets.\n\nHistorically, credit-based lending was reserved for $100M+ private deals. Now, with tokenized funds and DeFi rails, Drift unlocks access to strategies previously gated to larger institutions.",
      "isRepost": false,
      "originalAuthor": "DriftProtocol",
      "postUrl": "/DriftProtocol/status/1925218833738220024"
    },
    {
      "timestamp": "2025-05-21T15:13:24.000Z",
      "tweetText": "BREAKING: $BTC JUST HIT ATH",
      "isRepost": false,
      "originalAuthor": "DriftProtocol",
      "postUrl": "/DriftProtocol/status/1925208310388527347"
    },
    {
      "timestamp": "2025-05-21T14:09:23.000Z",
      "tweetText": "DRIFT DEFI DAY IS HAPPENING NOW\n\nLFG",
      "isRepost": true,
      "originalAuthor": "cindyleowtt",
      "postUrl": "/cindyleowtt/status/1925192200423420144"
    },
    {
      "timestamp": "2025-05-21T14:01:16.000Z",
      "tweetText": "Drift DeFi Day is LIVE!",
      "isRepost": false,
      "originalAuthor": "DriftProtocol",
      "postUrl": "/DriftProtocol/status/1925190158191640913"
    },
    {
      "timestamp": "2025-05-21T13:19:12.000Z",
      "tweetText": "Gm to all driftooors and everyone attending \n@DriftProtocol\n DeFi day!\n\nGoing live soon ~",
      "isRepost": true,
      "originalAuthor": "davijlu",
      "postUrl": "/davijlu/status/1925179572334538899"
    },
    {
      "timestamp": "2025-05-21T11:45:03.000Z",
      "tweetText": "gm nyc \n\ndrift defi day happens today!",
      "isRepost": true,
      "originalAuthor": "spicycilipadi",
      "postUrl": "/spicycilipadi/status/1925155875947504036"
    },
    {
      "timestamp": "2025-05-20T18:30:44.000Z",
      "tweetText": "Juicy yield on Drift Amplify's JLP/USDC market with 5x strategy!",
      "isRepost": false,
      "originalAuthor": "DriftProtocol",
      "postUrl": "/DriftProtocol/status/1924895582868713944"
    },
    {
      "timestamp": "2025-05-20T18:30:47.000Z",
      "tweetText": "Amplify Now:",
      "isRepost": false,
      "originalAuthor": "DriftProtocol",
      "postUrl": "/DriftProtocol/status/1924895594763714700"
    },
    {
      "timestamp": "2025-05-20T18:30:50.000Z",
      "tweetText": "Disclaimer: Yields are variable and may fluctuate based on market conditions. Past performance is not indicative of future results.",
      "isRepost": false,
      "originalAuthor": "DriftProtocol",
      "postUrl": "/DriftProtocol/status/1924895606952362464"
    },
    {
      "timestamp": "2025-05-20T16:21:33.000Z",
      "tweetText": "Get 69 DRIFT for your thoughtful product feedback! \n\nTo qualify:\n- You must be giving feedback for the first time\n\n- DM \n@0xMinhdonz\n with detailed insights and answer any follow-up questions\n\n- Open to re-engage once updates are live or for future beta testing",
      "isRepost": false,
      "originalAuthor": "DriftProtocol",
      "postUrl": "/DriftProtocol/status/1924863071421354421"
    }
  ]
}